{"protocol":{"minReaderVersion":1,"minWriterVersion":2}}
{"metaData":{"id":"20d975d3-36aa-4523-9dd5-74be2ab52e1e","format":{"provider":"parquet","options":{}},"schemaString":"{\"type\":\"struct\",\"fields\":[{\"name\":\"empno\",\"type\":\"long\",\"nullable\":true,\"metadata\":{}},{\"name\":\"ename\",\"type\":\"string\",\"nullable\":true,\"metadata\":{}},{\"name\":\"job\",\"type\":\"string\",\"nullable\":true,\"metadata\":{}},{\"name\":\"mgr\",\"type\":\"long\",\"nullable\":true,\"metadata\":{}},{\"name\":\"hiredate\",\"type\":\"date\",\"nullable\":true,\"metadata\":{}},{\"name\":\"sal\",\"type\":\"long\",\"nullable\":true,\"metadata\":{}},{\"name\":\"comm\",\"type\":\"long\",\"nullable\":true,\"metadata\":{}},{\"name\":\"deptno\",\"type\":\"long\",\"nullable\":true,\"metadata\":{}}]}","partitionColumns":[],"configuration":{"description":"emp"},"createdTime":1660219489416}}
{"commitInfo":{"timestamp":1660219489486,"operation":"CREATE OR REPLACE TABLE","operationParameters":{"isManaged":"false","description":null,"partitionBy":"[]","properties":"{\"description\":\"emp\"}"},"isolationLevel":"Serializable","isBlindAppend":true,"operationMetrics":{},"engineInfo":"Apache-Spark/3.2.0 Delta-Lake/2.0.0","txnId":"5d8eef81-85eb-4f5f-a98b-7854ca19ffba"}}
