{"remove":{"path":"part-00003-d9d0d597-ed5a-4e6a-8595-bb20a597068b-c000.snappy.parquet","deletionTimestamp":1659924243829,"dataChange":true,"extendedFileMetadata":true,"partitionValues":{},"size":486}}
{"remove":{"path":"part-00001-3e0ce6da-6a88-48d5-846a-d5a62580b232-c000.snappy.parquet","deletionTimestamp":1659924243829,"dataChange":true,"extendedFileMetadata":true,"partitionValues":{},"size":478}}
{"add":{"path":"part-00000-9a6dd420-40ec-4ec4-9047-8ee0368a6907-c000.snappy.parquet","partitionValues":{},"size":486,"modificationTime":1659924243821,"dataChange":true,"stats":"{\"numRecords\":2,\"minValues\":{\"id\":9},\"maxValues\":{\"id\":108},\"nullCount\":{\"id\":0}}"}}
{"add":{"path":"part-00001-159d343b-ac05-4e72-a5e8-f6be51d04dab-c000.snappy.parquet","partitionValues":{},"size":478,"modificationTime":1659924243817,"dataChange":true,"stats":"{\"numRecords\":1,\"minValues\":{\"id\":106},\"maxValues\":{\"id\":106},\"nullCount\":{\"id\":0}}"}}
{"commitInfo":{"timestamp":1659924243831,"operation":"UPDATE","operationParameters":{"predicate":"((id#1806L % 2) = 0)"},"readVersion":26,"isolationLevel":"Serializable","isBlindAppend":false,"operationMetrics":{"numRemovedFiles":"2","numCopiedRows":"1","numAddedChangeFiles":"0","executionTimeMs":"2404","scanTimeMs":"2091","numAddedFiles":"2","numUpdatedRows":"2","rewriteTimeMs":"311"},"engineInfo":"Apache-Spark/3.2.0 Delta-Lake/2.0.0","txnId":"221c3637-c9a1-44ab-8bcf-f26f573509c9"}}
