{"remove":{"path":"part-00003-32c80041-870b-43cc-98c7-0a6d03fa2630-c000.snappy.parquet","deletionTimestamp":1660003558905,"dataChange":true,"extendedFileMetadata":true,"partitionValues":{},"size":486}}
{"remove":{"path":"part-00001-46955d68-1f97-4201-9715-99a107fa84c3-c000.snappy.parquet","deletionTimestamp":1660003558905,"dataChange":true,"extendedFileMetadata":true,"partitionValues":{},"size":478}}
{"add":{"path":"part-00000-db909831-0121-42af-b200-f914176a7958-c000.snappy.parquet","partitionValues":{},"size":486,"modificationTime":1660003558894,"dataChange":true,"stats":"{\"numRecords\":2,\"minValues\":{\"id\":9},\"maxValues\":{\"id\":108},\"nullCount\":{\"id\":0}}"}}
{"add":{"path":"part-00001-d37a5a97-35f2-41ef-ba6e-ff875a5b00a7-c000.snappy.parquet","partitionValues":{},"size":478,"modificationTime":1660003558890,"dataChange":true,"stats":"{\"numRecords\":1,\"minValues\":{\"id\":106},\"maxValues\":{\"id\":106},\"nullCount\":{\"id\":0}}"}}
{"commitInfo":{"timestamp":1660003558908,"operation":"UPDATE","operationParameters":{"predicate":"((id#1806L % 2) = 0)"},"readVersion":75,"isolationLevel":"Serializable","isBlindAppend":false,"operationMetrics":{"numRemovedFiles":"2","numCopiedRows":"1","numAddedChangeFiles":"0","executionTimeMs":"2139","scanTimeMs":"1835","numAddedFiles":"2","numUpdatedRows":"2","rewriteTimeMs":"303"},"engineInfo":"Apache-Spark/3.2.0 Delta-Lake/2.0.0","txnId":"7fb606b6-d717-424c-a271-0660479ca4df"}}
